MANIFEST.in
setup.py
examples/.DS_Store
examples/dragon_pygame.py
examples/goblins_pygame.py
examples/mix_pygame.py
examples/powerup_pygame.py
examples/spine_pygame.py
examples/spinosaurus_pygame.py
examples/data/.DS_Store
examples/data/dragon.atlas
examples/data/dragon.json
examples/data/dragon.png
examples/data/dragon2.png
examples/data/goblins.atlas
examples/data/goblins.json
examples/data/goblins.png
examples/data/goblins2.png
examples/data/powerup.atlas
examples/data/powerup.json
examples/data/powerup.png
examples/data/spineboy.atlas
examples/data/spineboy.json
examples/data/spineboy.png
examples/data/spineboy2.atlas
examples/data/spineboy2.png
examples/data/spinosaurus.atlas
examples/data/spinosaurus.json
examples/data/spinosaurus.png
examples/data/blarg/.DS_Store
pyguts.egg-info/PKG-INFO
pyguts.egg-info/SOURCES.txt
pyguts.egg-info/dependency_links.txt
pyguts.egg-info/requires.txt
pyguts.egg-info/top_level.txt
src/Atlas.py
src/AtlasAttachmentLoader.py
src/RegionAttachment.py
src/Skeleton.py
src/__init__.py