Metadata-Version: 1.0
Name: pyguts
Version: 1.0b14
Summary: A pygame front-end for spine-python.
Home-page: https://github.com/terrysimons/spine-python/pyguts
Author: Terry Simons
Author-email: terry.simons@gmail.com
License: UNKNOWN
Platform: UNKNOWN
Classifier: License :: OSI Approved :: BSD License
